README.rst
setup.py
juju_dbinspect/__init__.py
juju_dbinspect/cli.py
juju_dbinspect/config.py
juju_dbinspect/entities.py
juju_dbinspect/exceptions.py
juju_dbinspect/identity.py
juju_dbinspect/relhist.py
juju_dbinspect.egg-info/PKG-INFO
juju_dbinspect.egg-info/SOURCES.txt
juju_dbinspect.egg-info/dependency_links.txt
juju_dbinspect.egg-info/entry_points.txt
juju_dbinspect.egg-info/requires.txt
juju_dbinspect.egg-info/top_level.txt
juju_dbinspect/tests/__init__.py
juju_dbinspect/tests/base.py
juju_dbinspect/tests/test_config.py