Metadata-Version: 1.1
Name: juju-dbinspect
Version: 0.1.5
Summary: Juju database introspection
Home-page: https://github.com/kapilt/juju-dbinspect
Author: Kapil Thangavelu
Author-email: kapil.foss@gmail.com
License: BSD
Platform: UNKNOWN
Classifier: Intended Audience :: Developers
Classifier: Programming Language :: Python
Classifier: Operating System :: OS Independent
